setup.py
redfox/__init__.py
redfox/meta.py
redfox/request.py
redfox/routing.py
redfox.egg-info/PKG-INFO
redfox.egg-info/SOURCES.txt
redfox.egg-info/dependency_links.txt
redfox.egg-info/entry_points.txt
redfox.egg-info/requires.txt
redfox.egg-info/top_level.txt