Metadata-Version: 1.0
Name: redfox
Version: 1.1
Summary: WSGI request routing for Python objects
Home-page: http://code.google.com/p/python-redfox/
Author: Owen Jacobson
Author-email: owen.jacobson@grimoire.ca
License: UNKNOWN
Download-URL: http://code.google.com/p/python-redfox/downloads/list
Platform: UNKNOWN
Classifier: Development Status :: 5 - Production/Stable
Classifier: Environment :: Web Environment
Classifier: Framework :: Paste
Classifier: Intended Audience :: Developers
Classifier: License :: OSI Approved :: MIT License
Classifier: Operating System :: OS Independent
Classifier: Topic :: Internet :: WWW/HTTP :: WSGI
Classifier: Topic :: Software Development :: Libraries :: Application Frameworks
